my_toy_package/__init__.py
my_toy_package/cli.py
my_toy_package/my_toy_package.py
my_toy_package/SubPackage1/MyClass1.py
my_toy_package/SubPackage1/__init__.py
my_toy_package/SubPackage2/MyClass2.py
my_toy_package/SubPackage2/MyClass3.py
my_toy_package/SubPackage2/__init__.py
my_toy_package-0.9.0.dist-info/AUTHORS.rst
my_toy_package-0.9.0.dist-info/LICENSE
my_toy_package-0.9.0.dist-info/METADATA
my_toy_package-0.9.0.dist-info/WHEEL
my_toy_package-0.9.0.dist-info/entry_points.txt
my_toy_package-0.9.0.dist-info/top_level.txt
my_toy_package-0.9.0.dist-info/RECORD
