Metadata-Version: 2.1
Name: my-toy-package
Version: 0.9.0
Summary: My Toy Package shows how to create and maintain a package.
Home-page: https://github.com/francois-durand/my_toy_package
Author: François Durand
Author-email: fradurand@gmail.com
License: GNU General Public License v3
Keywords: my_toy_package
Platform: UNKNOWN
Classifier: Development Status :: 2 - Pre-Alpha
Classifier: Intended Audience :: Developers
Classifier: License :: OSI Approved :: GNU General Public License v3 (GPLv3)
Classifier: Natural Language :: English
Classifier: Programming Language :: Python :: 3
Classifier: Programming Language :: Python :: 3.5
Classifier: Programming Language :: Python :: 3.6
Classifier: Programming Language :: Python :: 3.7
Requires-Dist: Click (>=6.0)
